eml_analyzer/__init__.py
eml_analyzer/cli_script.py
eml_analyzer/library/__init__.py
eml_analyzer/library/outputs/__init__.py
eml_analyzer/library/outputs/abstract_output.py
eml_analyzer/library/outputs/json_output.py
eml_analyzer/library/outputs/standard_output.py
eml_analyzer/library/parser/__init__.py
eml_analyzer/library/parser/attachment.py
eml_analyzer/library/parser/parsed_email.py
eml_analyzer/library/parser/printable_filename.py
eml_analyzer/library/parser/structure_item.py
eml_analyzer-3.0.1.dist-info/LICENSE
eml_analyzer-3.0.1.dist-info/METADATA
eml_analyzer-3.0.1.dist-info/WHEEL
eml_analyzer-3.0.1.dist-info/entry_points.txt
eml_analyzer-3.0.1.dist-info/top_level.txt
eml_analyzer-3.0.1.dist-info/RECORD
