Metadata-Version: 2.1
Name: eml-analyzer
Version: 3.0.1
Summary: A cli script to analyze an E-Mail in the eml format for viewing the header, extracting attachments, etc.
Home-page: https://github.com/wahlflo/eml_analyzer
Author: Florian Wahl
Author-email: florian.wahl.developer@gmail.com
Classifier: Programming Language :: Python :: 3
Classifier: License :: OSI Approved :: MIT License
Classifier: Operating System :: OS Independent
License-File: LICENSE
Requires-Dist: cli-formatter (>=1.2.0)
